trio_paho_mqtt/__init__.py
trio_paho_mqtt/client.py
trio_paho_mqtt/py.typed
trio_paho_mqtt_up1-0.4.1.dist-info/LICENSE
trio_paho_mqtt_up1-0.4.1.dist-info/WHEEL
trio_paho_mqtt_up1-0.4.1.dist-info/METADATA
trio_paho_mqtt_up1-0.4.1.dist-info/RECORD
