Metadata-Version: 2.1
Name: trio-paho-mqtt-up1
Version: 0.4.1
Summary: MQTT support for the Trio async runtime using Paho (update fork)
License: Apache-2.0
Author: Olivier (fork)
Author-email: triopahomqtt.python@librepush.net
Requires-Python: >=3.8,<4.0
Classifier: License :: OSI Approved :: Apache Software License
Classifier: Programming Language :: Python :: 3
Classifier: Programming Language :: Python :: 3.8
Classifier: Programming Language :: Python :: 3.9
Classifier: Programming Language :: Python :: 3.10
Requires-Dist: paho-mqtt (>=1.6.1,<2.0.0)
Requires-Dist: trio (>=0.21.0,<0.22.0)
